css_generator/__init__.py
css_generator/_version.py
css_generator/enums.py
css_generator/styleparser.py
css_generator-0.1.1.dist-info/LICENSE
css_generator-0.1.1.dist-info/METADATA
css_generator-0.1.1.dist-info/WHEEL
css_generator-0.1.1.dist-info/top_level.txt
css_generator-0.1.1.dist-info/RECORD
