Metadata-Version: 2.1
Name: css-generator
Version: 0.1.1
Summary: CSS stylesheet generator
Home-page: UNKNOWN
Author: Hugo Paquet
License: MIT
Platform: UNKNOWN
